pyliven/__init__.py
pyliven/exceptions.py
pyliven/liven.py
pyliven-0.1.1.dist-info/METADATA
pyliven-0.1.1.dist-info/WHEEL
pyliven-0.1.1.dist-info/licenses/LICENSE
pyliven-0.1.1.dist-info/RECORD
