Metadata-Version: 2.3
Name: pyliven
Version: 0.1.1
Summary: Stateful variables in Python, a new way to calculate
Project-URL: Documentation, https://keymii.github.io/pyliven/
Project-URL: Repository, https://github.com/Keymii/pyliven/
Project-URL: Issues, https://github.com/Keymii/pyliven/issues
Author-email: Abhijat Bharadwaj <bharadwaj.abhijat@yahoo.com>
Maintainer-email: Abhijat Bharadwaj <bharadwaj.abhijat@yahoo.com>
License: MIT License
License-File: LICENSE
Keywords: live,numeric,python,stateful,variables
Classifier: Development Status :: 5 - Production/Stable
Classifier: Intended Audience :: Developers
Classifier: License :: OSI Approved :: MIT License
Classifier: Programming Language :: Python :: 3
Requires-Python: >=3.5
